component/__init__.py
component/analyzer.py
component/debug.py
component/host.py
component/metadata.py
component/provider.py
component/py.typed
component/schema.py
component/util.py
pulumi_components_test-0.0.7.dist-info/METADATA
pulumi_components_test-0.0.7.dist-info/WHEEL
pulumi_components_test-0.0.7.dist-info/RECORD
