Metadata-Version: 2.4
Name: pulumi-components-test
Version: 0.0.7
Summary: This is a proof of concept to build a provider from Python code using type annotations to define the schema.
Requires-Python: >=3.12
Requires-Dist: pulumi>=3.145.0
